CHANGELOG.rst
LICENSE
MANIFEST.in
README.rst
setup.py
djangotoolbox/__init__.py
djangotoolbox/admin.py
djangotoolbox/errorviews.py
djangotoolbox/fields.py
djangotoolbox/http.py
djangotoolbox/middleware.py
djangotoolbox/models.py
djangotoolbox/test.py
djangotoolbox/tests.py
djangotoolbox/utils.py
djangotoolbox/widgets.py
djangotoolbox.egg-info/PKG-INFO
djangotoolbox.egg-info/SOURCES.txt
djangotoolbox.egg-info/dependency_links.txt
djangotoolbox.egg-info/top_level.txt
djangotoolbox/db/__init__.py
djangotoolbox/db/base.py
djangotoolbox/db/basecompiler.py
djangotoolbox/db/creation.py
djangotoolbox/db/utils.py
djangotoolbox/sites/__init__.py
djangotoolbox/sites/dynamicsite.py